djsci/.DS_Store
djsci/__init__.py
djsci/admin.py
djsci/apps.py
djsci/migrations/.DS_Store
djsci/migrations/0001_initial.py
djsci/migrations/__init__.py
djsci/models.py
djsci/tests.py
djsci/urls.py
djsci/views.py
djsci-0.0.0.0.dist-info/METADATA
djsci-0.0.0.0.dist-info/WHEEL
djsci-0.0.0.0.dist-info/RECORD
